griffin/__init__.py
griffin/__main__.py
griffin/_filters.py
griffin/cli.py
griffin/config.py
griffin/core.py
griffin/logger.py
griffin/utils.py
griffin-0.0.1.dev1.dist-info/DESCRIPTION.rst
griffin-0.0.1.dev1.dist-info/entry_points.txt
griffin-0.0.1.dev1.dist-info/METADATA
griffin-0.0.1.dev1.dist-info/metadata.json
griffin-0.0.1.dev1.dist-info/RECORD
griffin-0.0.1.dev1.dist-info/top_level.txt
griffin-0.0.1.dev1.dist-info/WHEEL
